README.md
setup.py
entrypoints/__init__.py
entrypoints/cli.py
entrypoints/server.py
text_categorization/__init__.py
text_categorization/categorizer.py
text_categorization/examples.txt
text_categorization/llms.py
text_categorization/template.txt
text_categorization/tools.py
text_categorization/vectorstore.py
text_categorization.egg-info/PKG-INFO
text_categorization.egg-info/SOURCES.txt
text_categorization.egg-info/dependency_links.txt
text_categorization.egg-info/entry_points.txt
text_categorization.egg-info/requires.txt
text_categorization.egg-info/top_level.txt